{
  "gold": {
    "domain": "simonsports.bet",
    "canonicalUrl": "https://simonsports.bet/",
    "themeName": "gold",
    "accent": "#c79442",
    "accentSoft": "#f4dfae",
    "surfaceTop": "#f7f9fc",
    "surfaceBottom": "#9da8b7",
    "icon": "ssb-gold-v1.ico",
    "touchIcon": "ssb-gold-touch-v1-180.png",
    "manifest": "manifest-gold-v1.json",
    "manifestBackground": "#f2dfb1",
    "manifestTheme": "#c79442",
    "manifestIcons": [
      {"src": "ssb-gold-v1-192.png", "sizes": "192x192", "type": "image/png"},
      {"src": "ssb-gold-v1-512.png", "sizes": "512x512", "type": "image/png"}
    ],
    "extraAssets": ["ssb-gold-v1-64.png", "ssb-gold-v1-128.png"],
    "shareImage": "ssb-share-v3.png",
    "logo": "ssb_full_logo_web_768.png"
  },
  "silver": {
    "domain": "simonsportsbetting.com",
    "canonicalUrl": "https://simonsportsbetting.com/",
    "themeName": "silver",
    "accent": "#8f9aa9",
    "accentSoft": "#d7dde6",
    "surfaceTop": "#f7f9fc",
    "surfaceBottom": "#9da8b7",
    "icon": "favicon.ico",
    "touchIcon": "ssb-touch-v3-180.png",
    "manifest": "manifest.json",
    "manifestBackground": "#d7dde6",
    "manifestTheme": "#8f9aa9",
    "manifestIcons": [
      {"src": "ssb-touch-v3-180.png", "sizes": "180x180", "type": "image/png", "purpose": "any"}
    ],
    "extraAssets": ["ssb-favicon-v3-64.png", "ssb-favicon-v3-128.png"],
    "shareImage": "ssb-share-v3.png",
    "logo": "ssb_full_logo_web_768.png"
  }
}
